irrelevant_content_detection/__init__.py
irrelevant_content_detection/detector.py
irrelevant_content_detection-0.3.dist-info/METADATA
irrelevant_content_detection-0.3.dist-info/WHEEL
irrelevant_content_detection-0.3.dist-info/top_level.txt
irrelevant_content_detection-0.3.dist-info/RECORD
