Metadata-Version: 2.1
Name: irrelevant-content-detection
Version: 0.3
Summary: A Python package for detecting irrelevant content in text and HTML.
Home-page: https://github.com/berkbirkan/irrelevant-content-detection
Author: Berk Birkan
Author-email: info@berkbirkan.com
Classifier: Programming Language :: Python :: 3
Classifier: License :: OSI Approved :: MIT License
Classifier: Operating System :: OS Independent
Requires-Python: >=3.6
Requires-Dist: numpy
Requires-Dist: scikit-learn
Requires-Dist: scipy
Requires-Dist: beautifulsoup4
